sqsx/__init__.py
sqsx/exceptions.py
sqsx/helper.py
sqsx/queue.py
sqsx-0.7.0.dist-info/licenses/LICENSE
tests/__init__.py
tests/conftest.py
tests/test_helper.py
tests/test_queue.py
sqsx-0.7.0.dist-info/METADATA
sqsx-0.7.0.dist-info/WHEEL
sqsx-0.7.0.dist-info/top_level.txt
sqsx-0.7.0.dist-info/RECORD
