Metadata-Version: 2.4
Name: sqsx
Version: 0.7.0
Summary: A simple task processor for Amazon SQS
Home-page: https://github.com/allisson/pysqsx
Author: Allisson Azevedo
Author-email: allisson@gmail.com
Keywords: aws,sqs
Classifier: Development Status :: 4 - Beta
Classifier: Intended Audience :: Developers
Classifier: License :: OSI Approved :: MIT License
Classifier: Programming Language :: Python :: 3.9
Classifier: Programming Language :: Python :: 3.10
Classifier: Programming Language :: Python :: 3.11
Classifier: Programming Language :: Python :: 3.12
Classifier: Programming Language :: Python :: 3.13
Classifier: Programming Language :: Python :: 3.14
License-File: LICENSE
Requires-Dist: boto3>=1.33.13
Requires-Dist: pydantic>=2.5.2
Dynamic: author
Dynamic: author-email
Dynamic: classifier
Dynamic: description
Dynamic: description-content-type
Dynamic: home-page
Dynamic: keywords
Dynamic: license-file
Dynamic: requires-dist
Dynamic: summary
